{"stats":{"minecraft:custom":{"minecraft:jump":73,"minecraft:time_since_rest":12293,"minecraft:crouch_one_cm":68,"minecraft:damage_dealt":20,"minecraft:sprint_one_cm":1422,"minecraft:leave_game":3,"minecraft:play_time":12293,"minecraft:damage_taken":50,"minecraft:time_since_death":12293,"minecraft:walk_one_cm":7961,"minecraft:sneak_time":25,"minecraft:climb_one_cm":1771,"minecraft:total_world_time":12293,"minecraft:fall_one_cm":2515,"minecraft:fly_one_cm":4262},"minecraft:picked_up":{"pvz_zengarden:zengarden_guide":1,"minecraft:wooden_sword":1,"minecraft:oak_log":2,"minecraft:wooden_axe":1},"minecraft:mined":{"minecraft:oak_leaves":1}},"DataVersion":3465}